{
  "items": [],
  "activity": [
    {
      "id": "fa_1772720344924_g7vcta",
      "at": "2026-03-05T14:19:04.924Z",
      "type": "deleted",
      "by": "MITMAX",
      "feedbackId": "fb_1772720327501_vxq4mp",
      "feedbackTitle": "sdfdsfsdfsdfdsf",
      "details": {
        "deletedStatus": "open",
        "createdBy": "MITMAX"
      }
    },
    {
      "id": "fa_1772720341803_exfnbx",
      "at": "2026-03-05T14:19:01.803Z",
      "type": "updated",
      "by": "MITMAX",
      "feedbackId": "fb_1772720327501_vxq4mp",
      "feedbackTitle": "sdfdsfsdfsdfdsf",
      "details": {
        "fromStatus": "open",
        "toStatus": "open"
      }
    },
    {
      "id": "fa_1772720336489_up8dsh",
      "at": "2026-03-05T14:18:56.489Z",
      "type": "updated",
      "by": "MITMAX",
      "feedbackId": "fb_1772720327501_vxq4mp",
      "feedbackTitle": "sdfsdf",
      "details": {
        "fromStatus": "open",
        "toStatus": "open"
      }
    },
    {
      "id": "fa_1772720327501_1vidr8",
      "at": "2026-03-05T14:18:47.501Z",
      "type": "created",
      "by": "MITMAX",
      "feedbackId": "fb_1772720327501_vxq4mp",
      "feedbackTitle": "he",
      "details": {}
    },
    {
      "id": "fa_1772720316893_ou6k6b",
      "at": "2026-03-05T14:18:36.893Z",
      "type": "deleted",
      "by": "MITMAX",
      "feedbackId": "fb_1772720313724_9u0t2c",
      "feedbackTitle": "Untitled Feedback",
      "details": {
        "deletedStatus": "open",
        "createdBy": "MITMAX"
      }
    },
    {
      "id": "fa_1772720313725_f51yt4",
      "at": "2026-03-05T14:18:33.725Z",
      "type": "created",
      "by": "MITMAX",
      "feedbackId": "fb_1772720313724_9u0t2c",
      "feedbackTitle": "Untitled Feedback",
      "details": {}
    }
  ]
}